MANIFEST.in
README.rst
setup.cfg
setup.py
yaml2sql/__init__.py
yaml2sql/cli.py
yaml2sql/sqls.py
yaml2sql/version.py
yaml2sql.egg-info/PKG-INFO
yaml2sql.egg-info/SOURCES.txt
yaml2sql.egg-info/dependency_links.txt
yaml2sql.egg-info/entry_points.txt
yaml2sql.egg-info/requires.txt
yaml2sql.egg-info/top_level.txt