Metadata-Version: 1.2
Name: yaml2sql
Version: 0.0.1
Summary: Create SQL statements from data models in YAML files.
Home-page: https://github.com/Bit-a-Bit-gh/yaml2sql
Author: Bit-a-Bit
Author-email: hola@bit-a-bit.info
License: GPLv3
Download-URL: https://github.com/Bit-a-Bit-gh/yaml2sql/archive/0.0.1.tar.gz
Keywords: sql,yaml,data models
Platform: UNKNOWN
Classifier: Development Status :: 3 - Alpha
Classifier: Intended Audience :: Developers
Classifier: Topic :: Software Development :: Libraries
Classifier: License :: OSI Approved :: GNU General Public License v3 (GPLv3)
Classifier: Programming Language :: Python :: 3.8
Requires-Python: >=0.0.1
